peng3d_sphinxext
